hackmd_mcp/__init__.py
hackmd_mcp/__main__.py
hackmd_mcp/hackmd_mcp_server.py
hackmd_mcp-0.2.3.dist-info/LICENSE
hackmd_mcp-0.2.3.dist-info/METADATA
hackmd_mcp-0.2.3.dist-info/WHEEL
hackmd_mcp-0.2.3.dist-info/entry_points.txt
hackmd_mcp-0.2.3.dist-info/top_level.txt
hackmd_mcp-0.2.3.dist-info/RECORD
