Metadata-Version: 2.1
Name: hackmd-mcp
Version: 0.2.3
Summary: HackMD MCP - 命令行工具與 MCP 服務
Home-page: https://github.com/yourusername/hackmd-mcp
Author: Oliver
Author-email: your.email@example.com
Classifier: Programming Language :: Python :: 3
Classifier: License :: OSI Approved :: MIT License
Classifier: Operating System :: OS Independent
Requires-Python: >=3.7
License-File: LICENSE
Requires-Dist: httpx>=0.20.0
Requires-Dist: pydantic>=2.0.0
Requires-Dist: mcp>=0.3.0
